datapath_design_21104051.sv
// Code your design here
module datapath(eqz, ldA,ldB,ldP,clrP,decB, clk,data_in);
input ldA,ldB,ldP,clrP,decB, clk;
input [15:0] data_in;
output eqz;

wire [15:0] A_out, P_out, B_out, z;

// "A" register data_in nunchi data teeskoni, control signal activate ayitey, A_out istaadi
pipo1 g1(A_out, data_in,ldA,clk);
// "P" register "z" nunchi data teeskoni, control signal activate ayitey, P_out istaadi
pipo2 g2(P_out, z,ldP,clrP,clk);
// "B" register data_in nunchi data teeskoni, control signal activate ayitey, B_out istaadi
cntr g3(B_out, data_in,ldB,decB,clk);
// add A nd P
addr g4(z, A_out,P_out);
// "B_out" zero aaa kaada ani check cheyadaniki
cmprtrB g5(eqz, B_out);

endmodule

//--------------------
// 2. pipo1 design	|
//--------------------
module pipo1(dout, data, load, clk);
input [15:0] data;
input load, clk;
output reg [15:0] dout;

always@(posedge clk)
	if(load)
		dout <= data;
endmodule

//--------------------
// 3. pipo2 design	|
//--------------------
module pipo2(dout, data, load, clr, clk);
input [15:0] data;
input load, clr, clk;
output reg [15:0] dout;

always@(posedge clk)
	begin
	if(clr)
		dout <= 16'b0;
	else if(load)
		dout <= data;
	end
endmodule

//--------------------
// 3. adder design	|
//--------------------
module addr(a_out, in1, in2);
input [15:0] in1, in2;
output reg [15:0] a_out;

always@(*)
	a_out = in1 + in2;
endmodule

//------------------------
// 4. comparator design	|
//------------------------
module cmprtrB(c_out, in);
input [15:0] in;
output c_out;

assign c_out = ~|(in);
endmodule

//----------------------
// 5. counter design	|
//----------------------
module cntr(c_out, data,load,dec,clk);
input [15:0] data;
input load, dec, clk;
output reg [15:0] c_out;

always@(posedge clk)
	if(load)
		c_out <= data;
	else if(dec)
		c_out <= c_out-1;
endmodule

//----------------------------
// 6. control path design	|
//----------------------------
module controller(ldA,ldB,ldP,clrP,decB,done, clk,eqz,start);
input clk,eqz,start;
output reg ldA,ldB,ldP,clrP,decB,done;

reg [2:0] state;
parameter s0=3'b000, s1=3'b001, s2=3'b010, s3=3'b011, s4=3'b100;

always@(posedge clk)
	begin
	case(state)
		s0 : if(start) state <= s1;
		s1 : state <= s2;
		s2 : state <= s3;
		s3 : #2 if(eqz == 0) state <= s3;
			 else state <= s4;
	//	s3 : #2 if(eqz) state <= s4;	// illaga kuuda raayochu
		s4 : state <= s4;
		default : state <= s0;
	endcase
	end

always@(state)
	begin
	case(state)
		s0 : begin #1 ldA=0; ldB=0; ldP=0; clrP=0; decB=0; end
		s1 : begin #1 ldA=1; end
		s2 : begin #1 ldA=0; ldB=1; clrP=1; end
		s3 : begin #1 ldB=0; ldP=1; clrP=0; decB=1; end
		s4 : begin #1 ldP=0; decB=0; done=1; end
		default : begin #1 ldA=0; ldB=0; ldP=0; clrP=0; decB=0; end
	endcase
	end
endmodule

datapath_tb_21104051.sv
// Code your testbench here
// or browse Examples
module above_test;
reg start, clk;
reg [15:0] data_in;
wire done;
wire eqz,ldA,ldB,ldP,clrP,decB;
  
datapath DP(eqz, ldA,ldB,ldP,clrP,decB, clk,data_in);
controller CON(ldA,ldB,ldP,clrP,decB,done, clk,eqz,start);

initial
	begin
		clk = 1'b0;
		#3 start=1'b1;
		#500 $finish;
	end
	
always #5 clk = ~clk;

initial
	begin
		#17 data_in = 17;
		#10 data_in = 5;
	end

initial
	begin
      $monitor($time," product = %d, multiplication_completed = %b", DP.P_out, 				done);
      $dumpfile("dump.vcd"); 
      $dumpvars(0,above_test);
	end

endmodule

dump_21104051.vcd
$date
	Thu Aug 25 17:46:37 2022
$end
$version
	Icarus Verilog
$end
$timescale
	1s
$end
$scope module above_test $end
$var wire 1 ! clrP $end
$var wire 1 " decB $end
$var wire 1 # done $end
$var wire 1 $ eqz $end
$var wire 1 % ldA $end
$var wire 1 & ldB $end
$var wire 1 ' ldP $end
$var reg 1 ( clk $end
$var reg 16 ) data_in [15:0] $end
$var reg 1 * start $end
$scope module DP $end
$var wire 16 + A_out [15:0] $end
$var wire 16 , B_out [15:0] $end
$var wire 16 - P_out [15:0] $end
$var wire 1 . clk $end
$var wire 1 ! clrP $end
$var wire 16 / data_in [15:0] $end
$var wire 1 " decB $end
$var wire 1 $ eqz $end
$var wire 1 % ldA $end
$var wire 1 & ldB $end
$var wire 1 ' ldP $end
$var wire 16 0 z [15:0] $end
$scope module g1 $end
$var wire 1 . clk $end
$var wire 16 1 data [15:0] $end
$var wire 1 % load $end
$var reg 16 2 dout [15:0] $end
$upscope $end
$scope module g2 $end
$var wire 1 . clk $end
$var wire 1 ! clr $end
$var wire 16 3 data [15:0] $end
$var wire 1 ' load $end
$var reg 16 4 dout [15:0] $end
$upscope $end
$scope module g3 $end
$var wire 1 . clk $end
$var wire 16 5 data [15:0] $end
$var wire 1 " dec $end
$var wire 1 & load $end
$var reg 16 6 c_out [15:0] $end
$upscope $end
$scope module g4 $end
$var wire 16 7 in1 [15:0] $end
$var wire 16 8 in2 [15:0] $end
$var reg 16 9 a_out [15:0] $end
$upscope $end
$scope module g5 $end
$var wire 1 $ c_out $end
$var wire 16 : in [15:0] $end
$upscope $end
$upscope $end
$scope module CON $end
$var wire 1 . clk $end
$var wire 1 $ eqz $end
$var wire 1 ; start $end
$var reg 1 < clrP $end
$var reg 1 = decB $end
$var reg 1 > done $end
$var reg 1 ? ldA $end
$var reg 1 @ ldB $end
$var reg 1 A ldP $end
$var reg 3 B state [2:0] $end
$upscope $end
$upscope $end
$enddefinitions $end
#0
$dumpvars
bx B
xA
x@
x?
x>
x=
x<
x;
bx :
bx 9
bx 8
bx 7
bx 6
bx 5
bx 4
bx 3
bx 2
bx 1
bx 0
bx /
0.
bx -
bx ,
bx +
x*
bx )
0(
x'
x&
x%
x$
x#
x"
x!
$end
#3
1*
1;
#5
b0 B
1(
1.
#6
0=
0"
0<
0!
0A
0'
0@
0&
0?
0%
#10
0(
0.
#15
b1 B
1(
1.
#16
1?
1%
#17
b10001 )
b10001 /
b10001 1
b10001 5
#20
0(
0.
#25
b10001 2
b10001 +
b10001 7
b10 B
1(
1.
#26
1<
1!
1@
1&
0?
0%
#27
b101 )
b101 /
b101 1
b101 5
#30
0(
0.
#35
b10001 9
b10001 0
b10001 3
b11 B
b101 6
0$
b101 ,
b101 :
b0 4
b0 -
b0 8
1(
1.
#36
1=
1"
0<
0!
1A
1'
0@
0&
#40
0(
0.
#45
b100010 9
b100010 0
b100010 3
b10001 4
b10001 -
b10001 8
b100 6
b100 ,
b100 :
1(
1.
#50
0(
0.
#55
b110011 9
b110011 0
b110011 3
b11 6
b11 ,
b11 :
b100010 4
b100010 -
b100010 8
1(
1.
#60
0(
0.
#65
b1000100 9
b1000100 0
b1000100 3
b110011 4
b110011 -
b110011 8
b10 6
b10 ,
b10 :
1(
1.
#70
0(
0.
#75
b1010101 9
b1010101 0
b1010101 3
b1 6
b1 ,
b1 :
b1000100 4
b1000100 -
b1000100 8
1(
1.
#80
0(
0.
#85
b1100110 9
b1100110 0
b1100110 3
b1010101 4
b1010101 -
b1010101 8
b0 6
1$
b0 ,
b0 :
1(
1.
#87
b100 B
#88
1>
1#
0=
0"
0A
0'
